setup.py
torender/__init__.py
torender/decorators.py
torender.egg-info/PKG-INFO
torender.egg-info/SOURCES.txt
torender.egg-info/dependency_links.txt
torender.egg-info/not-zip-safe
torender.egg-info/requires.txt
torender.egg-info/top_level.txt