Metadata-Version: 1.0
Name: torender
Version: 0.1.0
Summary: A prerender middleware for the tornado web framework
Home-page: http://github.com/dailymuse/torender
Author: Yusuf Simonson
Author-email: yusuf@themuse.com
License: UNKNOWN
Platform: UNKNOWN
